think/__init__.py
think/collections.py
think/core.py
think/datetimes.py
think/gradients.py
think/integers.py
think/internals.py
think/log.py
think/ops.py
think/pretty.py
think/strings.py
think/thoughts.py
think/fast/__init__.py
think/slow/__init__.py
think/slow/meta.py
think/slow/poly.py
think/slow/strong.py
thnk-0.0.3.dist-info/METADATA
thnk-0.0.3.dist-info/WHEEL
thnk-0.0.3.dist-info/top_level.txt
thnk-0.0.3.dist-info/RECORD
