Metadata-Version: 2.4
Name: thnk
Version: 0.0.3
Summary: A machine-learnable version of the python object system.
Author-email: Jason Wilkes <notarealdeveloper@gmail.com>
Project-URL: source, https://github.com/notarealdeveloper/think
Project-URL: download, https://pypi.org/project/thnk/#files
Requires-Dist: jax
Requires-Dist: tmstr
Requires-Dist: is_instance
Provides-Extra: develop
Requires-Dist: build; extra == "develop"
Requires-Dist: pytest; extra == "develop"
